a_simple_module_kul/__init__.py
a_simple_module_kul/add.py
a_simple_module_kul/helloworld.py
a_simple_module_kul/setup.py
a_simple_module_kul/subtract.py
a_simple_module_kul/extras/__init__.py
a_simple_module_kul/extras/divide.py
a_simple_module_kul/extras/multiply.py
a_simple_module_kul/extras/power.py
a_simple_module_kul-0.0.5.dist-info/METADATA
a_simple_module_kul-0.0.5.dist-info/WHEEL
a_simple_module_kul-0.0.5.dist-info/top_level.txt
a_simple_module_kul-0.0.5.dist-info/RECORD
