Metadata-Version: 2.1
Name: a-simple-module-kul
Version: 0.0.5
Summary: my first python package
Author: Stijn Dom
Author-email: stijn.dom@hotmail.be
Keywords: python,first package,math,university
Classifier: Development Status :: 1 - Planning
Classifier: Intended Audience :: Education
Classifier: Programming Language :: Python :: 3
Classifier: Operating System :: MacOS :: MacOS X
Classifier: Operating System :: Microsoft :: Windows
